README.md
setup.py
tplate/__init__.py
tplate/commandline.py
tplate.egg-info/PKG-INFO
tplate.egg-info/SOURCES.txt
tplate.egg-info/dependency_links.txt
tplate.egg-info/entry_points.txt
tplate.egg-info/requires.txt
tplate.egg-info/top_level.txt