Metadata-Version: 2.1
Name: tplate
Version: 1.0.3
Summary: A project templating tool that based on Jina2
Home-page: https://github.com/wrmay/tplate
Author: Randy May
License: MIT
Platform: UNKNOWN
